username/__init__.py
username-2.1.0.dist-info/METADATA
username-2.1.0.dist-info/WHEEL
username-2.1.0.dist-info/top_level.txt
username-2.1.0.dist-info/RECORD
