Metadata-Version: 2.1
Name: username
Version: 2.1.0
Summary: Get the current username
Home-page: https://projects.abranhe.com/username
Author: Abraham Hernandez
Author-email: abraham@abranhe.com
License: MIT
Project-URL: Source, https://github.com/abranhe/lupe
Keywords: cli command-line-interface python bash-tool username
Platform: UNKNOWN
Classifier: Programming Language :: Python
Classifier: Natural Language :: English
Classifier: Environment :: Plugins
Classifier: Intended Audience :: Developers
Classifier: License :: OSI Approved :: MIT License
Classifier: Programming Language :: Python :: 3
Classifier: Programming Language :: Python :: 3.2
Classifier: Programming Language :: Python :: 3.3
Classifier: Programming Language :: Python :: 3.4
Classifier: Operating System :: OS Independent
Classifier: Operating System :: MacOS
Classifier: Operating System :: Unix
